{
  "numOfAllStereotypes": 88,
  "numOfCoveredStereotypes": 88,
  "numOfAllPublicProperties": 46,
  "numOfCoveredPublicProperties": 46,
  "coveredStereotypes": [
    "SysML::Activities::Continuous",
    "SysML::Activities::ControlOperator",
    "SysML::Activities::Discrete",
    "SysML::Activities::NoBuffer",
    "SysML::Activities::Optional",
    "SysML::Activities::Overwrite",
    "SysML::Activities::Probability",
    "SysML::Activities::Rate",
    "SysML::Allocations::Allocate",
    "SysML::Allocations::AllocateActivityPartition",
    "SysML::Blocks::AdjunctProperty",
    "SysML::Blocks::BindingConnector",
    "SysML::Blocks::Block",
    "SysML::Blocks::BoundReference",
    "SysML::Blocks::ClassifierBehaviorProperty",
    "SysML::Blocks::ConnectorProperty",
    "SysML::Blocks::DistributedProperty",
    "SysML::Blocks::EndPathMultiplicity",
    "SysML::Blocks::NestedConnectorEnd",
    "SysML::Blocks::ParticipantProperty",
    "SysML::Blocks::PropertySpecificType",
    "SysML::Blocks::ValueType",
    "SysML::ConstraintBlocks::ConstraintBlock",
    "SysML::DeprecatedElements::Allocated",
    "SysML::DeprecatedElements::FlowPort",
    "SysML::DeprecatedElements::FlowSpecification",
    "SysML::DeprecatedElements::RequirementRelated",
    "SysML::ModelElements::Conform",
    "SysML::ModelElements::ElementGroup",
    "SysML::ModelElements::Expose",
    "SysML::ModelElements::Problem",
    "SysML::ModelElements::Rationale",
    "SysML::ModelElements::Stakeholder",
    "SysML::ModelElements::View",
    "SysML::ModelElements::Viewpoint",
    "SysML::Non-Normative Extensions::Activity::Essential",
    "SysML::Non-Normative Extensions::Activity::System process",
    "SysML::Non-Normative Extensions::Activity::effbd",
    "SysML::Non-Normative Extensions::Activity::nonStreaming",
    "SysML::Non-Normative Extensions::Activity::streaming",
    "SysML::Non-Normative Extensions::Actors::Actuator",
    "SysML::Non-Normative Extensions::Actors::Boundary system",
    "SysML::Non-Normative Extensions::Actors::Environmental effect",
    "SysML::Non-Normative Extensions::Actors::External system",
    "SysML::Non-Normative Extensions::Actors::Sensor",
    "SysML::Non-Normative Extensions::Actors::User system",
    "SysML::Non-Normative Extensions::Block::Domain",
    "SysML::Non-Normative Extensions::Block::External",
    "SysML::Non-Normative Extensions::Block::Subsystem",
    "SysML::Non-Normative Extensions::Block::System",
    "SysML::Non-Normative Extensions::Block::System context",
    "SysML::Non-Normative Extensions::Diagrams::BlockHierarchy",
    "SysML::Non-Normative Extensions::Diagrams::ContextDiagram",
    "SysML::Non-Normative Extensions::Diagrams::Diagram Description",
    "SysML::Non-Normative Extensions::Diagrams::SwimLaneDiagram",
    "SysML::Non-Normative Extensions::Diagrams::diagramUsage",
    "SysML::Non-Normative Extensions::Distributions::BasicInterval",
    "SysML::Non-Normative Extensions::Distributions::Interval",
    "SysML::Non-Normative Extensions::Distributions::Normal",
    "SysML::Non-Normative Extensions::Distributions::Uniform",
    "SysML::Non-Normative Extensions::Parametric::moe",
    "SysML::Non-Normative Extensions::Parametric::objectiveFunction",
    "SysML::Non-Normative Extensions::Requirement::businessRequirement",
    "SysML::Non-Normative Extensions::Requirement::designConstraint",
    "SysML::Non-Normative Extensions::Requirement::extendedRequirement",
    "SysML::Non-Normative Extensions::Requirement::functionalRequirement",
    "SysML::Non-Normative Extensions::Requirement::interfaceRequirement",
    "SysML::Non-Normative Extensions::Requirement::performanceRequirement",
    "SysML::Non-Normative Extensions::Requirement::physicalRequirement",
    "SysML::Non-Normative Extensions::Requirement::usabilityRequirement",
    "SysML::Ports&Flows::AcceptChangeStructuralFeatureEventAction",
    "SysML::Ports&Flows::ChangeStructuralFeatureEvent",
    "SysML::Ports&Flows::DirectedFeature",
    "SysML::Ports&Flows::FlowProperty",
    "SysML::Ports&Flows::FullPort",
    "SysML::Ports&Flows::InterfaceBlock",
    "SysML::Ports&Flows::InvocationOnNestedPortAction",
    "SysML::Ports&Flows::ItemFlow",
    "SysML::Ports&Flows::ProxyPort",
    "SysML::Ports&Flows::TriggerOnNestedPort",
    "SysML::Requirements::Copy",
    "SysML::Requirements::DeriveReqt",
    "SysML::Requirements::Refine",
    "SysML::Requirements::Requirement",
    "SysML::Requirements::Satisfy",
    "SysML::Requirements::TestCase",
    "SysML::Requirements::Trace",
    "SysML::Requirements::Verify"
  ],
  "uncoveredStereotypes": [],
  "coveredPublicProperties": [
    "SysML::Activities::Probability::probability",
    "SysML::Activities::Rate::rate",
    "SysML::Blocks::AdjunctProperty::principal",
    "SysML::Blocks::Block::isEncapsulated",
    "SysML::Blocks::BoundReference::bindingPath",
    "SysML::Blocks::BoundReference::boundEnd",
    "SysML::Blocks::ConnectorProperty::connector",
    "SysML::Blocks::DirectedRelationshipPropertyPath::sourceContext",
    "SysML::Blocks::DirectedRelationshipPropertyPath::sourcePropertyPath",
    "SysML::Blocks::DirectedRelationshipPropertyPath::targetContext",
    "SysML::Blocks::DirectedRelationshipPropertyPath::targetPropertyPath",
    "SysML::Blocks::ElementPropertyPath::propertyPath",
    "SysML::Blocks::EndPathMultiplicity::lower",
    "SysML::Blocks::EndPathMultiplicity::upper",
    "SysML::Blocks::ParticipantProperty::end",
    "SysML::Blocks::ValueType::quantityKind",
    "SysML::Blocks::ValueType::unit",
    "SysML::ModelElements::ElementGroup::criterion",
    "SysML::ModelElements::ElementGroup::member",
    "SysML::ModelElements::ElementGroup::name",
    "SysML::ModelElements::ElementGroup::orderedMember",
    "SysML::ModelElements::ElementGroup::size",
    "SysML::ModelElements::Stakeholder::concern",
    "SysML::ModelElements::Stakeholder::concernList",
    "SysML::ModelElements::View::stakeholder",
    "SysML::ModelElements::View::viewPoint",
    "SysML::ModelElements::Viewpoint::concern",
    "SysML::ModelElements::Viewpoint::concernList",
    "SysML::ModelElements::Viewpoint::language",
    "SysML::ModelElements::Viewpoint::method",
    "SysML::ModelElements::Viewpoint::presentation",
    "SysML::ModelElements::Viewpoint::purpose",
    "SysML::ModelElements::Viewpoint::stakeholder",
    "SysML::Ports&Flows::ChangeStructuralFeatureEvent::structuralFeature",
    "SysML::Ports&Flows::DirectedFeature::featureDirection",
    "SysML::Ports&Flows::InvocationOnNestedPortAction::onNestedPort",
    "SysML::Ports&Flows::TriggerOnNestedPort::onNestedPort",
    "SysML::Requirements::AbstractRequirement::Derived",
    "SysML::Requirements::AbstractRequirement::DerivedFrom",
    "SysML::Requirements::AbstractRequirement::Id",
    "SysML::Requirements::AbstractRequirement::Master",
    "SysML::Requirements::AbstractRequirement::RefinedBy",
    "SysML::Requirements::AbstractRequirement::SatisfiedBy",
    "SysML::Requirements::AbstractRequirement::Text",
    "SysML::Requirements::AbstractRequirement::TracedTo",
    "SysML::Requirements::AbstractRequirement::VerifiedBy"
  ],
  "uncoveredPublicProperties": []
}